dicomcat/__init__.py
dicomcat/cli.py
dicomcat/dicomcat.py
dicomcat/tests/assets/example_dicoms/BrainExample/brain_001.dcm
dicomcat/tests/assets/example_dicoms/BrainExample/brain_002.dcm
dicomcat/tests/assets/example_dicoms/BrainExample/brain_003.dcm
dicomcat/tests/assets/example_dicoms/BrainExample/brain_004.dcm
dicomcat/tests/assets/example_dicoms/BrainExample/brain_005.dcm
dicomcat/tests/assets/example_dicoms/BrainExample/brain_006.dcm
dicomcat/tests/assets/example_dicoms/BrainExample/brain_007.dcm
dicomcat/tests/assets/example_dicoms/BrainExample/brain_008.dcm
dicomcat/tests/assets/example_dicoms/BrainExample/brain_009.dcm
dicomcat/tests/assets/example_dicoms/BrainExample/brain_010.dcm
dicomcat/tests/assets/example_dicoms/BrainExample/brain_011.dcm
dicomcat/tests/assets/example_dicoms/BrainExample/brain_012.dcm
dicomcat/tests/assets/example_dicoms/BrainExample/brain_013.dcm
dicomcat/tests/assets/example_dicoms/BrainExample/brain_014.dcm
dicomcat/tests/assets/example_dicoms/BrainExample/brain_015.dcm
dicomcat/tests/assets/example_dicoms/BrainExample/brain_016.dcm
dicomcat/tests/assets/example_dicoms/BrainExample/brain_017.dcm
dicomcat/tests/assets/example_dicoms/BrainExample/brain_018.dcm
dicomcat/tests/assets/example_dicoms/BrainExample/brain_019.dcm
dicomcat/tests/assets/example_dicoms/BrainExample/brain_020.dcm
dicomcat/tests/assets/example_dicoms/Head/vhm.1001.dcm
dicomcat/tests/assets/example_dicoms/Head/vhm.1002.dcm
dicomcat/tests/assets/example_dicoms/Head/vhm.1003.dcm
dicomcat/tests/assets/example_dicoms/Head/vhm.1004.dcm
dicomcat/tests/assets/example_dicoms/Head/vhm.1005.dcm
dicomcat/tests/assets/example_dicoms/Head/vhm.1006.dcm
dicomcat/tests/assets/example_dicoms/Head/vhm.1007.dcm
dicomcat/tests/assets/example_dicoms/Head/vhm.1008.dcm
dicomcat/tests/assets/example_dicoms/Head/vhm.1009.dcm
dicomcat/tests/assets/example_dicoms/Head/vhm.1010.dcm
dicomcat/tests/assets/example_dicoms/Head/vhm.1011.dcm
dicomcat/tests/assets/example_dicoms/Head/vhm.1012.dcm
dicomcat-0.1.dist-info/LICENSE
dicomcat-0.1.dist-info/METADATA
dicomcat-0.1.dist-info/WHEEL
dicomcat-0.1.dist-info/entry_points.txt
dicomcat-0.1.dist-info/top_level.txt
dicomcat-0.1.dist-info/RECORD
