Metadata-Version: 2.1
Name: dicomcat
Version: 0.1
Summary: A simple python-based tool based on imgcat for displaying DICOM files in iTerm2.
Home-page: https://github.com/rwindsor1/DICOMcat
Author: Rhydian Windsor
Author-email: windsorrhydian@gmail.com
License: MIT
Platform: UNKNOWN
